<document>
  <properties>
    <title>Developer changes</title>
    <author email="tryggvi@idega.com">Tryggvi Larusson</author>
  </properties>
  <body>
  
  	<release version="3.1.5" date="2008-02-19">
      <action dev="alexis" type="update">
		Added the session polling property as a checkbox into Application Properties
      </action>
    </release>
    
    <release version="3.1.4" date="2007-07-12">
      <action dev="palli" type="update">
		Updated core reference so that new FileUtil is used.
      </action>
    </release>

    <release version="3.1.3" date="2007-06-28">
      <action dev="gimmi" type="fix">
		Fixed property settings to NOT rewrite every propertyfile on every change to a bundle
      </action>
      <action dev="gimmi" type="update">
      	Updated to core 3.1.52, builder 3.1.9, user 3.1.9
      </action>
    </release>

    <release version="3.1.2" date="2007-05-31">
      <action dev="eiki" type="update">
      	Added syntax coloring support to the SQLQueryer
      </action>
    </release>
    
  	<release version="3.1.1" date="2007-01-30">
      <action dev="eiki" type="update">
      	Changed LocaleSetter so you can disable english all together.
      </action>
    </release>
    
  	<release version="3.1.0" date="2005-06-19">
      <action dev="tryggvil" type="update">
      	Declaration of version for including in ePlatform release 3.1
      </action>
      <action dev="tryggvil" type="update">
      	Update of UI to be integrated into the platform 3 Workspace environment and
      	user the workspace stylesheets.
      </action>
    </release>

	<release version="1.2.3" date="2005-09-15">
      <action dev="tryggvil" type="update">
        Declaration of version for use core 3.0.6.
      </action>              
    </release>
          <release version="1.2.2" date="2005-05-25">
      <action dev="tryggvil" type="update">
        Declaration of version for use core 3.0.5.
      </action>              
    </release>
        <release version="1.2.1" date="2005-04-06">
      <action dev="tryggvil" type="update">
        Declaration of version for use core 3.0.4.
      </action>              
    </release>
      <release version="1.2.0" date="2005-03-11">
      <action dev="tryggvil" type="update">
        Declaration of version for use login 1.1.1.
      </action>              
    </release>
    <release version="1.1.0" date="2005-03-10">
      <action dev="tryggvil" type="update">
        Declaration of version for use in new systems based on JSF.
      </action>              
    </release>

    <release version="1.0" date="2004-07-21">
      <action dev="tryggvil" type="update">
        Declaration of version for use in old style systems.
      </action>              
    </release>

  </body>
</document>
